flask_hookserver.py
Flask_Hookserver-1.1.0.dist-info/DESCRIPTION.rst
Flask_Hookserver-1.1.0.dist-info/METADATA
Flask_Hookserver-1.1.0.dist-info/RECORD
Flask_Hookserver-1.1.0.dist-info/WHEEL
Flask_Hookserver-1.1.0.dist-info/metadata.json
Flask_Hookserver-1.1.0.dist-info/top_level.txt
