Metadata-Version: 2.0
Name: Flask-Hookserver
Version: 1.1.0
Summary: Server for GitHub webhooks using Flask
Home-page: https://github.com/nickfrostatx/flask-hookserver
Author: Nick Frost
Author-email: nickfrostatx@gmail.com
License: MIT
Keywords: github,webhooks,flask
Platform: UNKNOWN
Classifier: Development Status :: 5 - Production/Stable
Classifier: Framework :: Flask
Classifier: Intended Audience :: Developers
Classifier: Intended Audience :: System Administrators
Classifier: License :: OSI Approved :: MIT License
Classifier: Programming Language :: Python
Classifier: Programming Language :: Python :: 2.6
Classifier: Programming Language :: Python :: 2.7
Classifier: Programming Language :: Python :: 3
Classifier: Programming Language :: Python :: 3.3
Classifier: Programming Language :: Python :: 3.4
Classifier: Programming Language :: Python :: 3.5
Classifier: Programming Language :: Python :: Implementation :: CPython
Classifier: Programming Language :: Python :: Implementation :: PyPy
Classifier: Topic :: Software Development
Requires-Dist: Flask (>=0.9)
Requires-Dist: Werkzeug (>=0.7)
Requires-Dist: requests[security] (>=2.3.0)
